segmenthee/__init__.py
segmenthee/cart_api.py
segmenthee/config.py
segmenthee/parser_api.py
segmenthee/shop.py
segmentheepy_test-0.0.6.dist-info/METADATA
segmentheepy_test-0.0.6.dist-info/WHEEL
segmentheepy_test-0.0.6.dist-info/top_level.txt
segmentheepy_test-0.0.6.dist-info/RECORD
