Metadata-Version: 2.1
Name: segmentheepy-test
Version: 0.0.6
Summary: Segmenthee library
Author: Michaletzky Tamas
License: MIT
Requires-Python: >=3.8
Requires-Dist: user-agents (==2.2.0)
Requires-Dist: xgboost (==1.4.0)
Requires-Dist: scikit-learn (==0.23.2)
